deepquantum/__init__.py
deepquantum/adjoint.py
deepquantum/ansatz.py
deepquantum/bitmath.py
deepquantum/channel.py
deepquantum/circuit.py
deepquantum/communication.py
deepquantum/cutting.py
deepquantum/distributed.py
deepquantum/gate.py
deepquantum/layer.py
deepquantum/operation.py
deepquantum/optimizer.py
deepquantum/qasm3.py
deepquantum/qmath.py
deepquantum/qpd.py
deepquantum/state.py
deepquantum/utils.py
deepquantum/mbqc/__init__.py
deepquantum/mbqc/command.py
deepquantum/mbqc/operation.py
deepquantum/mbqc/pattern.py
deepquantum/mbqc/state.py
deepquantum/photonic/__init__.py
deepquantum/photonic/ansatz.py
deepquantum/photonic/channel.py
deepquantum/photonic/circuit.py
deepquantum/photonic/decompose.py
deepquantum/photonic/distributed.py
deepquantum/photonic/draw.py
deepquantum/photonic/gate.py
deepquantum/photonic/hafnian_.py
deepquantum/photonic/mapper.py
deepquantum/photonic/measurement.py
deepquantum/photonic/operation.py
deepquantum/photonic/qmath.py
deepquantum/photonic/state.py
deepquantum/photonic/tdm.py
deepquantum/photonic/torontonian_.py
deepquantum/photonic/utils.py
deepquantum/photonic/cache/Idx_2qb_6mode_aux_00.pickle
deepquantum/photonic/cache/Idx_2qb_6mode_aux_00.pt
deepquantum/photonic/cache/Idx_2qb_6mode_aux_10.pickle
deepquantum/photonic/cache/Idx_2qb_6mode_aux_10.pt
deepquantum/photonic/cache/Idx_3qb_8mode_aux_00.pickle
deepquantum/photonic/cache/Idx_3qb_8mode_aux_00.pt
deepquantum/photonic/cache/Idx_3qb_8mode_aux_10.pickle
deepquantum/photonic/cache/Idx_3qb_8mode_aux_10.pt
deepquantum/photonic/cache/Idx_4qb_10mode_aux_00.pickle
deepquantum/photonic/cache/Idx_4qb_10mode_aux_00.pt
deepquantum-4.4.0.dist-info/licenses/LICENSE
deepquantum-4.4.0.dist-info/METADATA
deepquantum-4.4.0.dist-info/WHEEL
deepquantum-4.4.0.dist-info/top_level.txt
deepquantum-4.4.0.dist-info/RECORD
