Metadata-Version: 2.4
Name: deepquantum
Version: 4.4.0
Summary: DeepQuantum for quantum computing
Author-email: TuringQ <Algorithms-Applications@turingq.com>, Junjie He <hejunjie@turingq.com>, Keming Hu <hukeming@turingq.com>, Yuze Zhu <zhuyuze@turingq.com>
Maintainer-email: Junjie He <hejunjie@turingq.com>
Project-URL: Homepage, https://deepquantum.turingq.com/
Project-URL: Documentation, https://dqapi.turingq.com/
Project-URL: Repository, https://github.com/TuringQ/deepquantum.git
Project-URL: Issues, https://github.com/TuringQ/deepquantum/issues
Keywords: quantum computing,quantum machine learning,photonic quantum computing
Classifier: Development Status :: 4 - Beta
Classifier: Intended Audience :: Developers
Classifier: Intended Audience :: Science/Research
Classifier: Programming Language :: Python :: 3
Classifier: Programming Language :: Python :: 3.9
Classifier: Programming Language :: Python :: 3.10
Classifier: Programming Language :: Python :: 3.11
Classifier: Programming Language :: Python :: 3.12
Classifier: Programming Language :: Python :: 3.13
Classifier: License :: OSI Approved :: Apache Software License
Classifier: Operating System :: OS Independent
Requires-Python: >=3.9
License-File: LICENSE
Requires-Dist: torch>=2.4.0
Requires-Dist: numpy
Requires-Dist: matplotlib
Requires-Dist: qiskit
Requires-Dist: pylatexenc
Requires-Dist: scipy
Requires-Dist: sympy
Requires-Dist: svgwrite
Requires-Dist: bayesian-optimization<2
Requires-Dist: networkx
Requires-Dist: tqdm
Requires-Dist: psutil
Provides-Extra: dev
Requires-Dist: pytest; extra == "dev"
Requires-Dist: perceval-quandela; extra == "dev"
Requires-Dist: strawberryfields; extra == "dev"
Requires-Dist: thewalrus; extra == "dev"
Requires-Dist: graphix==0.3.1; extra == "dev"
Dynamic: license-file
